yaclogger/__init__.py
yaclogger/yaclogger.py
dev_yet_another_colorful_logger-0.0.10.dist-info/LICENSE
dev_yet_another_colorful_logger-0.0.10.dist-info/METADATA
dev_yet_another_colorful_logger-0.0.10.dist-info/WHEEL
dev_yet_another_colorful_logger-0.0.10.dist-info/top_level.txt
dev_yet_another_colorful_logger-0.0.10.dist-info/RECORD
