Metadata-Version: 2.1
Name: dev-yet-another-colorful-logger
Version: 0.0.10
Summary: Just another Colorful Logger with my personal customizations to be used in any python script.
Home-page: https://github.com/wagnercotta/dev_yet_another_colorful_logger
Author: Wagner Cotta
License: GNU
Platform: UNKNOWN
License-File: LICENSE
Requires-Dist: colorlog
